README.rst
flask_classy.py
setup.py
Flask_Classy.egg-info/PKG-INFO
Flask_Classy.egg-info/SOURCES.txt
Flask_Classy.egg-info/dependency_links.txt
Flask_Classy.egg-info/not-zip-safe
Flask_Classy.egg-info/requires.txt
Flask_Classy.egg-info/top_level.txt